{
  "type": "FeatureCollection",
  "features": [
    {
      "type": "Feature",
      "geometry": {
        "type": "Point",
        "coordinates": [
          43.4002,
          10.5629
        ]
      },
      "properties": {
        "c": "7977bca3-3645-4072-bfe9-ad342c2674e8",
        "n": "Awdal",
        "u": "SOM_0001_V1",
        "b": [
          42.68301,
          9.65724,
          44.23613,
          11.5152
        ],
        "pc": [
          "a2006979-4f25-448c-891b-3935c4bcf6f0"
        ],
        "pu": [
          "SOM_V1"
        ]
      }
    },
    {
      "type": "Feature",
      "geometry": {
        "type": "Point",
        "coordinates": [
          43.8356,
          4.197
        ]
      },
      "properties": {
        "c": "2943bd42-b7c8-45b7-9967-250ba0a72eec",
        "n": "Bakool",
        "u": "SOM_0002_V1",
        "b": [
          42.88531,
          3.25153,
          44.80109,
          4.96044
        ],
        "pc": [
          "a2006979-4f25-448c-891b-3935c4bcf6f0"
        ],
        "pu": [
          "SOM_V1"
        ]
      }
    },
    {
      "type": "Feature",
      "geometry": {
        "type": "Point",
        "coordinates": [
          45.3253,
          2.0765
        ]
      },
      "properties": {
        "c": "01fbc793-6079-4340-81e3-9ed9b699caa2",
        "n": "Banadir",
        "u": "SOM_0003_0001_V1",
        "b": [
          45.20831,
          1.96833,
          45.60608,
          2.18504
        ],
        "pc": [
          "a2006979-4f25-448c-891b-3935c4bcf6f0"
        ],
        "pu": [
          "SOM_V1"
        ]
      }
    },
    {
      "type": "Feature",
      "geometry": {
        "type": "Point",
        "coordinates": [
          49.9727,
          10.1574
        ]
      },
      "properties": {
        "c": "3ee7ea44-a5c0-433d-b93d-122110a6ee5c",
        "n": "Bari",
        "u": "SOM_0004_V1",
        "b": [
          48.91851,
          8.32771,
          51.41508,
          11.98839
        ],
        "pc": [
          "a2006979-4f25-448c-891b-3935c4bcf6f0"
        ],
        "pu": [
          "SOM_V1"
        ]
      }
    },
    {
      "type": "Feature",
      "geometry": {
        "type": "Point",
        "coordinates": [
          43.5927,
          2.6955
        ]
      },
      "properties": {
        "c": "ef43390a-0275-4d43-b2e8-a8aba5c80404",
        "n": "Bay",
        "u": "SOM_0005_V1",
        "b": [
          42.40088,
          1.46173,
          44.6911,
          3.92151
        ],
        "pc": [
          "a2006979-4f25-448c-891b-3935c4bcf6f0"
        ],
        "pu": [
          "SOM_V1"
        ]
      }
    },
    {
      "type": "Feature",
      "geometry": {
        "type": "Point",
        "coordinates": [
          46.8982,
          4.9865
        ]
      },
      "properties": {
        "c": "a84aba36-823d-48e5-8a20-dd7685d24555",
        "n": "Galgaduud",
        "u": "SOM_0006_V1",
        "b": [
          45.48142,
          3.47327,
          47.82794,
          6.52119
        ],
        "pc": [
          "a2006979-4f25-448c-891b-3935c4bcf6f0"
        ],
        "pu": [
          "SOM_V1"
        ]
      }
    },
    {
      "type": "Feature",
      "geometry": {
        "type": "Point",
        "coordinates": [
          41.771,
          2.7711
        ]
      },
      "properties": {
        "c": "30052d36-45bb-46b2-83c8-63d642c22fb8",
        "n": "Gedo",
        "u": "SOM_0007_V1",
        "b": [
          40.99432,
          1.23272,
          43.14093,
          4.30793
        ],
        "pc": [
          "a2006979-4f25-448c-891b-3935c4bcf6f0"
        ],
        "pu": [
          "SOM_V1"
        ]
      }
    },
    {
      "type": "Feature",
      "geometry": {
        "type": "Point",
        "coordinates": [
          45.4929,
          4.3232
        ]
      },
      "properties": {
        "c": "a51dceb8-5861-4fe9-978e-b52f16eed328",
        "n": "Hiraan",
        "u": "SOM_0008_V1",
        "b": [
          44.5921,
          3.20148,
          46.40112,
          5.43306
        ],
        "pc": [
          "a2006979-4f25-448c-891b-3935c4bcf6f0"
        ],
        "pu": [
          "SOM_V1"
        ]
      }
    },
    {
      "type": "Feature",
      "geometry": {
        "type": "Point",
        "coordinates": [
          41.8602,
          -0.1646
        ]
      },
      "properties": {
        "c": "01da401b-09fc-4910-baa1-d42bdba5235a",
        "n": "Lower Juba",
        "u": "SOM_0009_V1",
        "b": [
          40.99565,
          -1.65684,
          43.19096,
          1.32172
        ],
        "pc": [
          "a2006979-4f25-448c-891b-3935c4bcf6f0"
        ],
        "pu": [
          "SOM_V1"
        ]
      }
    },
    {
      "type": "Feature",
      "geometry": {
        "type": "Point",
        "coordinates": [
          44.6598,
          1.9738
        ]
      },
      "properties": {
        "c": "1f8665a3-22d8-44ef-aaa7-7291c89b58db",
        "n": "Lower Shabelle",
        "u": "SOM_0010_V1",
        "b": [
          42.9809,
          0.67688,
          45.39111,
          3.27148
        ],
        "pc": [
          "a2006979-4f25-448c-891b-3935c4bcf6f0"
        ],
        "pu": [
          "SOM_V1"
        ]
      }
    },
    {
      "type": "Feature",
      "geometry": {
        "type": "Point",
        "coordinates": [
          42.8376,
          1.1541
        ]
      },
      "properties": {
        "c": "3d7e756f-8060-463e-ae20-b8b9be32e32f",
        "n": "Middle Juba",
        "u": "SOM_0011_V1",
        "b": [
          41.4209,
          0.31189,
          43.51978,
          1.95172
        ],
        "pc": [
          "a2006979-4f25-448c-891b-3935c4bcf6f0"
        ],
        "pu": [
          "SOM_V1"
        ]
      }
    },
    {
      "type": "Feature",
      "geometry": {
        "type": "Point",
        "coordinates": [
          45.8786,
          3.0272
        ]
      },
      "properties": {
        "c": "d7c57957-70cf-4e95-bc4d-c28e739b300a",
        "n": "Middle Shabelle",
        "u": "SOM_0012_V1",
        "b": [
          45.07111,
          2.15167,
          47.03687,
          3.89148
        ],
        "pc": [
          "a2006979-4f25-448c-891b-3935c4bcf6f0"
        ],
        "pu": [
          "SOM_V1"
        ]
      }
    },
    {
      "type": "Feature",
      "geometry": {
        "type": "Point",
        "coordinates": [
          48.2205,
          6.0194
        ]
      },
      "properties": {
        "c": "cefc6ec7-fd28-4151-8435-39144de1cb6d",
        "n": "Mudug",
        "u": "SOM_0013_V1",
        "b": [
          46.53848,
          4.33634,
          49.6469,
          7.71112
        ],
        "pc": [
          "a2006979-4f25-448c-891b-3935c4bcf6f0"
        ],
        "pu": [
          "SOM_V1"
        ]
      }
    },
    {
      "type": "Feature",
      "geometry": {
        "type": "Point",
        "coordinates": [
          49.1141,
          8.2722
        ]
      },
      "properties": {
        "c": "acf728d3-cf60-4ad7-9272-9a1f6f240fa3",
        "n": "Nugaal",
        "u": "SOM_0014_V1",
        "b": [
          47.55626,
          7.40365,
          50.17684,
          9.1405
        ],
        "pc": [
          "a2006979-4f25-448c-891b-3935c4bcf6f0"
        ],
        "pu": [
          "SOM_V1"
        ]
      }
    },
    {
      "type": "Feature",
      "geometry": {
        "type": "Point",
        "coordinates": [
          47.5304,
          10.4607
        ]
      },
      "properties": {
        "c": "84f8d8d7-cbb0-438b-b400-45a8f6ef784d",
        "n": "Sanaag",
        "u": "SOM_0015_V1",
        "b": [
          46.01111,
          9.42108,
          49.0611,
          11.32581
        ],
        "pc": [
          "a2006979-4f25-448c-891b-3935c4bcf6f0"
        ],
        "pu": [
          "SOM_V1"
        ]
      }
    },
    {
      "type": "Feature",
      "geometry": {
        "type": "Point",
        "coordinates": [
          47.5984,
          9.0384
        ]
      },
      "properties": {
        "c": "656e13a9-4ba0-433f-94bc-cebec0c73ad0",
        "n": "Sool",
        "u": "SOM_0016_V1",
        "b": [
          46.0495,
          8.00002,
          49.08112,
          10.05048
        ],
        "pc": [
          "a2006979-4f25-448c-891b-3935c4bcf6f0"
        ],
        "pu": [
          "SOM_V1"
        ]
      }
    },
    {
      "type": "Feature",
      "geometry": {
        "type": "Point",
        "coordinates": [
          45.4447,
          9.1446
        ]
      },
      "properties": {
        "c": "8bd15515-ea95-40de-bfa8-00813df2ccd3",
        "n": "Togdheer",
        "u": "SOM_0017_V1",
        "b": [
          44.6911,
          8.0,
          47.10107,
          10.1709
        ],
        "pc": [
          "a2006979-4f25-448c-891b-3935c4bcf6f0"
        ],
        "pu": [
          "SOM_V1"
        ]
      }
    },
    {
      "type": "Feature",
      "geometry": {
        "type": "Point",
        "coordinates": [
          44.1049,
          9.8221
        ]
      },
      "properties": {
        "c": "eb230a71-77e2-41b7-bc5e-1199b67c8290",
        "n": "Woqooyi Galbeed",
        "u": "SOM_0018_V1",
        "b": [
          43.28964,
          8.77173,
          46.03147,
          10.86867
        ],
        "pc": [
          "a2006979-4f25-448c-891b-3935c4bcf6f0"
        ],
        "pu": [
          "SOM_V1"
        ]
      }
    }
  ]
}